{
  "generatedAt": "2026-04-21T04:51:00.736Z",
  "release": {
    "packageVersion": "0.1.0",
    "harnessVersion": "0.1.0",
    "coreVersion": "0.1.0",
    "gitSha": "7c8074dd9671c5e6e97d09505acb1e2b57f259b1",
    "gitShortSha": "7c8074d",
    "gitBranch": "publish-q-win",
    "buildId": "0.1.0+7c8074d",
    "q": {
      "modelName": "Q",
      "foundationModel": "Gemma 4",
      "trainingLock": {
        "generatedAt": "2026-04-19T07:46:04Z",
        "lockVersion": 1,
        "bundleId": "q-defsec-code-longctx-harbor-opt-2384cf5-bench-v23-5ed19b9-286326ce",
        "runName": "q-defsec-code-longctx-harbor-opt-2384cf5-bench-v23",
        "modelName": "Q",
        "trainDatasetPath": ".training-output/q/q-defsec-code-longctx-harbor-opt-2384cf5-bench-v23.jsonl",
        "trainDatasetSha256": "286326ce786c0a9b9b4a636a38114cc221c1b978a083ca55d70cc6ca6172cb07",
        "trainDatasetRowCount": 117,
        "mixManifestPath": ".training-output/q/q-defsec-code-longctx-harbor-opt-2384cf5-bench-v23.manifest.json",
        "mixManifestSha256": "4c7df8284cedaf8e43f1715c8eaf4c30826687e27a5d511ef8ccd4ca78df991e",
        "mixSupplementalCount": 6,
        "mixSupplementalPaths": [
          "training/q/q_harness_identity_seed.json",
          "training/q/q_immaculate_reasoning_seed.json",
          "training/q/terminal_bench_semantic_seed.json",
          "training/q/bridgebench_seed.json",
          "training/q/coding_long_context_seed.json",
          ".training-output/q/q-failure-corpus.jsonl"
        ],
        "curationRunId": null,
        "lockPath": ".training-output/q/latest-training-lock.json"
      },
      "hybridSession": {
        "generatedAt": "2026-04-19T07:46:17Z",
        "sessionId": "q-hybrid-harbor-opt-2384cf5-bench-v23",
        "sessionPath": ".training-output/q/sessions/q-hybrid-harbor-opt-2384cf5-bench-v23/hybrid-session.json",
        "localStatus": "ready",
        "cloudStatus": "ready",
        "cloudProvider": "hf_jobs",
        "trainingBundleId": "q-defsec-code-longctx-harbor-opt-2384cf5-bench-v23-5ed19b9-286326ce",
        "immaculateBundleId": "immaculate-orchestration-5ed19b9-cd094c28",
        "immaculateBundlePath": ".training-output/immaculate/latest-training-bundle.json"
      }
    }
  },
  "surfaces": [
    {
      "label": "BridgeBench",
      "path": "docs\\wiki\\BridgeBench.json",
      "generatedAt": "2026-04-19T07:51:12.922Z"
    },
    {
      "label": "BridgeBench soak",
      "path": "docs\\wiki\\BridgeBench-Soak.json",
      "generatedAt": "2026-04-15T06:15:54.188Z"
    },
    {
      "label": "Q structured contract benchmark",
      "path": "docs\\wiki\\Model-Benchmark-Comparison.json",
      "generatedAt": "2026-04-19T07:48:09.656Z"
    },
    {
      "label": "Q readiness gate",
      "path": "docs\\wiki\\Q-Readiness-Gate.json",
      "generatedAt": "2026-04-21T04:50:54.293Z"
    },
    {
      "label": "Q gateway validation",
      "path": "docs\\wiki\\Q-Gateway-Validation.json",
      "generatedAt": "2026-04-19T07:47:33.854Z"
    },
    {
      "label": "Q gateway substrate",
      "path": "docs\\wiki\\Q-Gateway-Substrate.json",
      "generatedAt": "2026-04-19T22:06:38.757Z"
    },
    {
      "label": "Q mediation drift",
      "path": "docs\\wiki\\Q-Mediation-Drift.json",
      "generatedAt": "2026-04-19T22:06:40.025Z"
    },
    {
      "label": "Arobi audit integrity",
      "path": "docs\\wiki\\Arobi-Audit-Integrity.json",
      "generatedAt": "2026-04-19T23:41:05.513Z"
    },
    {
      "label": "Arobi live ledger receipt",
      "path": "docs\\wiki\\Arobi-Live-Ledger-Receipt.json",
      "generatedAt": "2026-04-20T17:22:38.533Z"
    },
    {
      "label": "Roundtable actionability",
      "path": "docs\\wiki\\Roundtable-Actionability.json",
      "generatedAt": "2026-04-21T04:49:52.630Z"
    },
    {
      "label": "Roundtable runtime",
      "path": "docs\\wiki\\Roundtable-Runtime.json",
      "generatedAt": "2026-04-21T04:50:38.849Z"
    },
    {
      "label": "Q API audit",
      "path": "docs\\wiki\\Q-API-Audit.json",
      "generatedAt": "2026-04-19T22:47:48Z"
    },
    {
      "label": "Arobi decision review",
      "path": "docs\\wiki\\Arobi-Decision-Review.json",
      "generatedAt": "2026-04-19T22:47:51.678Z"
    },
    {
      "label": "Q hybrid training",
      "path": "docs\\wiki\\Q-Hybrid-Training.json",
      "generatedAt": "2026-04-19T07:46:17Z"
    },
    {
      "label": "HF Jobs training",
      "path": "docs\\wiki\\HF-Jobs-Training.json",
      "generatedAt": "2026-04-19T05:52:40Z"
    },
    {
      "label": "Colab free training",
      "path": "docs\\wiki\\Colab-Free-Training.json",
      "generatedAt": "2026-04-19T05:52:29Z"
    },
    {
      "label": "Kaggle free training",
      "path": "docs\\wiki\\Kaggle-Free-Training.json",
      "generatedAt": "2026-04-19T05:52:00Z"
    },
    {
      "label": "Cloudflare Q inference",
      "path": "docs\\wiki\\Cloudflare-Q-Inference.json",
      "generatedAt": "2026-04-19T05:52:31Z"
    },
    {
      "label": "OCI GPU advisor",
      "path": "docs\\wiki\\OCI-GPU-Advisor.json",
      "generatedAt": "2026-04-19T07:46:17Z"
    },
    {
      "label": "OCI region capacity",
      "path": "docs\\wiki\\OCI-Region-Capacity.json",
      "generatedAt": "2026-04-17T02:02:24Z"
    },
    {
      "label": "Q benchmark corpus",
      "path": "docs\\wiki\\Q-Benchmark-Corpus.json",
      "generatedAt": "2026-04-21T04:50:54Z"
    },
    {
      "label": "Q benchmark promotion",
      "path": "docs\\wiki\\Q-Benchmark-Promotion.json",
      "generatedAt": "2026-04-19T07:46:03Z"
    },
    {
      "label": "W&B benchmark export",
      "path": "docs\\wiki\\Benchmark-Wandb-Export.json",
      "generatedAt": "2026-04-20T21:13:53.888521+00:00"
    },
    {
      "label": "Harbor terminal bench",
      "path": "docs\\wiki\\Harbor-Terminal-Bench.json",
      "generatedAt": "2026-04-19T07:43:17.831Z"
    },
    {
      "label": "Terminal-Bench public task",
      "path": "docs\\wiki\\Terminal-Bench-Public-Task.json",
      "generatedAt": "2026-04-19T14:31:45.217Z"
    },
    {
      "label": "Terminal-Bench leaderboard status",
      "path": "docs\\wiki\\Terminal-Bench-Receipt.json",
      "generatedAt": "2026-04-19T14:31:45.545Z"
    },
    {
      "label": "Terminal-Bench rerun (diagnostic-only)",
      "path": "docs\\wiki\\Terminal-Bench-Rerun.json",
      "generatedAt": "2026-04-19T14:31:45.730Z"
    },
    {
      "label": "GitHub checks receipt",
      "path": "docs\\wiki\\GitHub-Checks-Receipt.json",
      "generatedAt": "2026-04-16T17:54:12.583Z"
    },
    {
      "label": "Harbor terminal bench soak",
      "path": "docs\\wiki\\Harbor-Terminal-Bench-Soak.json",
      "generatedAt": "2026-04-16T13:05:24.510Z"
    },
    {
      "label": "Q benchmark sweep (60m)",
      "path": "docs\\wiki\\Q-Benchmark-Sweep-60m.json",
      "generatedAt": "2026-04-17T20:56:29.772Z"
    }
  ],
  "cloudflare": {
    "generatedAt": "2026-04-19T05:52:31Z",
    "sessionId": "q-hybrid-harbor-opt-2384cf5-bench-v22",
    "status": "auth-blocked",
    "authReady": false,
    "adapterReady": false,
    "workerReady": false,
    "evalBundleReady": true,
    "smokeReady": false,
    "recommendedNextStep": "Set CLOUDFLARE_ACCOUNT_ID, CLOUDFLARE_API_TOKEN, and CLOUDFLARE_Q_BASE_MODEL, then rerun the Cloudflare inference check."
  },
  "output": {
    "jsonPath": "docs\\wiki\\Release-Surface.json",
    "markdownPath": "docs\\wiki\\Release-Surface.md"
  }
}
